{
  "fields": [
    "business_sizes",
    "business_stages",
    "business_activity",
    "employ_eu_citizens",
    "industries",
    "intellectual_property",
    "personal_data",
    "public_sector_procurement",
    "eu_uk_government_funding",
    "regions",
    "regulations_and_standards",
    "sector_business_area",
    "types_of_support"
  ],

  "expanded_search_result_fields": {
    "types_of_support": [
      {
        "label": "Finance",
        "value": "finance"
      },
      {
        "label": "Equity",
        "value": "equity"
      },
      {
        "label": "Grant",
        "value": "grant"
      },
      {
        "label": "Loan",
        "value": "loan"
      },
      {
        "label": "Expertise and advice",
        "value": "expertise-and-advice"
      },
      {
        "label": "Recognition awards",
        "value": "recognition-award"
      }
    ],

    "business_stages": [
      {
        "label": "Not yet trading",
        "value": "not-yet-trading"
      },
      {
        "label": "Start-ups (1-2 years trading)",
        "value": "start-up"
      },
      {
        "label": "Established",
        "value": "established"
      }
    ],

    "industries": [
      {
        "label": "Agriculture and food",
        "value": "agriculture-and-food"
      },
      {
        "label": "Business and finance",
        "value": "business-and-finance"
      },
      {
        "label": "Construction",
        "value": "construction"
      },
      {
        "label": "Education",
        "value": "education"
      },
      {
        "label": "Health",
        "value": "health"
      },
      {
        "label": "Hospitality and catering",
        "value": "hospitality-and-catering"
      },
      {
        "label": "IT, digital and creative",
        "value": "information-technology-digital-and-creative"
      },
      {
        "label": "Manufacturing",
        "value": "manufacturing"
      },
      {
        "label": "Mining",
        "value": "mining"
      },
      {
        "label": "Real estate and property",
        "value": "real-estate-and-property"
      },
      {
        "label": "Science and technology",
        "value": "science-and-technology"
      },
      {
        "label": "Service industries",
        "value": "service-industries"
      },
      {
        "label": "Transport and distribution",
        "value": "transport-and-distribution"
      },
      {
        "label": "Travel and leisure",
        "value": "travel-and-leisure"
      },
      {
        "label": "Utilities providers",
        "value": "utilities-providers"
      },
      {
        "label": "Wholesale and retail",
        "value": "wholesale-and-retail"
      }
    ],

    "regions": [
      {"label": "East Midlands", "value": "east-midlands"},
      {"label": "Eastern", "value": "eastern"},
      {"label": "London", "value": "london"},
      {"label": "North East", "value": "north-east"},
      {"label": "North West", "value": "north-west"},
      {"label": "Northern Ireland", "value": "northern-ireland"},
      {"label": "Scotland", "value": "scotland"},
      {"label": "South East", "value": "south-east"},
      {"label": "South West", "value": "south-west"},
      {"label": "Wales", "value": "wales"},
      {"label": "West Midlands", "value": "west-midlands"},
      {"label": "Yorkshire and the Humber", "value": "yorkshire-and-the-humber"}
    ],

    "business_sizes": [
      {
        "label": "0 to 9 employees",
        "value": "under-10"
      },
      {
        "label": "10 to 249 employees",
        "value": "between-10-and-249"
      },
      {
        "label": "250 to 500 employees",
        "value": "between-250-and-500"
      },
      {
        "label": "More than 500 employees",
        "value": "over-500"
      }
    ]
  }
}
